odoo/addons/hr_employee_social_media/README.rst
odoo/addons/hr_employee_social_media/__init__.py
odoo/addons/hr_employee_social_media/__manifest__.py
odoo/addons/hr_employee_social_media/data/social_media.xml
odoo/addons/hr_employee_social_media/i18n/ar.po
odoo/addons/hr_employee_social_media/i18n/cs_CZ.po
odoo/addons/hr_employee_social_media/i18n/de.po
odoo/addons/hr_employee_social_media/i18n/es.po
odoo/addons/hr_employee_social_media/i18n/fi.po
odoo/addons/hr_employee_social_media/i18n/fr.po
odoo/addons/hr_employee_social_media/i18n/hr.po
odoo/addons/hr_employee_social_media/i18n/hr_HR.po
odoo/addons/hr_employee_social_media/i18n/hr_employee_social_media.pot
odoo/addons/hr_employee_social_media/i18n/it.po
odoo/addons/hr_employee_social_media/i18n/lt.po
odoo/addons/hr_employee_social_media/i18n/nl_NL.po
odoo/addons/hr_employee_social_media/i18n/pl.po
odoo/addons/hr_employee_social_media/i18n/pt_BR.po
odoo/addons/hr_employee_social_media/i18n/ro.po
odoo/addons/hr_employee_social_media/i18n/sl.po
odoo/addons/hr_employee_social_media/models/__init__.py
odoo/addons/hr_employee_social_media/models/hr_employee.py
odoo/addons/hr_employee_social_media/models/hr_social_media.py
odoo/addons/hr_employee_social_media/readme/CONTRIBUTORS.rst
odoo/addons/hr_employee_social_media/readme/DESCRIPTION.rst
odoo/addons/hr_employee_social_media/security/ir.model.access.csv
odoo/addons/hr_employee_social_media/static/description/icon.png
odoo/addons/hr_employee_social_media/static/description/index.html
odoo/addons/hr_employee_social_media/tests/__init__.py
odoo/addons/hr_employee_social_media/tests/test_social_media.py
odoo/addons/hr_employee_social_media/views/hr_employee_view.xml
odoo/addons/hr_employee_social_media/views/hr_social_media.xml
odoo11_addon_hr_employee_social_media-11.0.1.0.0.99.dev7.dist-info/METADATA
odoo11_addon_hr_employee_social_media-11.0.1.0.0.99.dev7.dist-info/WHEEL
odoo11_addon_hr_employee_social_media-11.0.1.0.0.99.dev7.dist-info/top_level.txt
odoo11_addon_hr_employee_social_media-11.0.1.0.0.99.dev7.dist-info/RECORD
